[
  {
    "functionLabel": "",
    "functionName": "LinearContrastStretching",
    "id": 0,
    "ifcond": "",
    "insert_position": "",
    "label": "",
    "pragma": {
      "name": "TOP",
      "option": [
        {
          "name": "name",
          "value": "LinearContrastStretching"
        }
      ]
    },
    "slx": false,
    "sourceFile": "/home/cristian/Documents/ACES/RC/assignment-3/vitis/solution/directives.tcl",
    "sourceLine": 7,
    "success": true
  },
  {
    "functionLabel": "",
    "functionName": "LinearContrastStretching",
    "id": 1,
    "ifcond": "",
    "insert_position": "",
    "label": "",
    "pragma": {
      "name": "TOP",
      "option": [
        {
          "name": "name",
          "value": "LinearContrastStretching"
        }
      ]
    },
    "slx": false,
    "sourceFile": "/home/cristian/Documents/ACES/RC/assignment-3/vitis/solution/csynth.tcl",
    "sourceLine": 17,
    "success": true
  }
]